oa_tsp.py
oa_tsp-0.0.1.dist-info/LICENSE
oa_tsp-0.0.1.dist-info/METADATA
oa_tsp-0.0.1.dist-info/WHEEL
oa_tsp-0.0.1.dist-info/top_level.txt
oa_tsp-0.0.1.dist-info/RECORD
