Metadata-Version: 2.1
Name: oa-tsp
Version: 0.0.1
Summary: TSP using simulated annealing
Author: The OA
Classifier: Programming Language :: Python :: 3
Classifier: License :: OSI Approved :: MIT License
Classifier: Operating System :: OS Independent
Requires-Python: >=3.6
License-File: LICENSE
